README.md
setup.py
python_telegram_bot_pagination.egg-info/PKG-INFO
python_telegram_bot_pagination.egg-info/SOURCES.txt
python_telegram_bot_pagination.egg-info/dependency_links.txt
python_telegram_bot_pagination.egg-info/top_level.txt
telegram_bot_pagination/__init__.py