Metadata-Version: 2.1
Name: python-telegram-bot-pagination
Version: 0.0.3
Summary: Python inline keyboard pagination for Telegram Bot API
Home-page: https://github.com/ksinn/python-telegram-bot-pagination
Author: ksinn
Author-email: ksinnd@gmail.com
License: GPL2
Keywords: telegram bot api pagination keyboard inline tools
Platform: UNKNOWN
